classy_start/__init__.py
classy_start/cli.py
classy_start/file_contents.py
classy_start/paths.py
classy_start/start.py
classy_start/conf/__init__.py
classy_start/conf/app_template/__init__.py-tpl
classy_start/conf/app_template/apps.py-tpl
classy_start/conf/app_template/models.py-tpl
classy_start/conf/app_template/views.py-tpl
classy_start/conf/app_template/migrations/__init__.py-tpl
classy_start/conf/app_template/tests/__init__.py-tpl
classy_start/conf/project_template/gitignore.py-tpl
classy_start/conf/project_template/manage.py-tpl
classy_start/conf/project_template/requirements.py-tpl
classy_start/conf/project_template/secrets.py-tpl
classy_start/conf/project_template/project_name/__init__.py-tpl
classy_start/conf/project_template/project_name/asgi.py-tpl
classy_start/conf/project_template/project_name/settings.py-tpl
classy_start/conf/project_template/project_name/urls.py-tpl
classy_start/conf/project_template/project_name/wsgi.py-tpl
django_classy_start-0.0.2.dist-info/LICENSE
django_classy_start-0.0.2.dist-info/METADATA
django_classy_start-0.0.2.dist-info/WHEEL
django_classy_start-0.0.2.dist-info/entry_points.txt
django_classy_start-0.0.2.dist-info/top_level.txt
django_classy_start-0.0.2.dist-info/RECORD
