Metadata-Version: 2.1
Name: django-classy-start
Version: 0.0.2
Summary: A command line utility for starting Django projects and apps in a most classy manner
Home-page: https://github.com/mfonism/django-classy-start
Author: Mfon Eti-mfon
Author-email: mfon@etimfon.com
License: UNKNOWN
Platform: UNKNOWN
Classifier: Development Status :: 4 - Beta
Classifier: Environment :: Web Environment
Classifier: Framework :: Django
Classifier: Framework :: Django :: 3.1
Classifier: Programming Language :: Python
Classifier: Programming Language :: Python :: 3.6
Classifier: Programming Language :: Python :: 3.7
Classifier: Programming Language :: Python :: 3.8
Classifier: License :: OSI Approved :: MIT License
Classifier: Operating System :: OS Independent
Classifier: Topic :: Software Development :: Libraries :: Python Modules
Requires-Python: >=3.6
Requires-Dist: Django (>=3.1)
Requires-Dist: python-dotenv (>=0.14.0)
